ambr/__init__.py
ambr/client.py
ambr/constants.py
ambr/enums.py
ambr/exceptions.py
ambr/utils.py
ambr/models/__init__.py
ambr/models/_base.py
ambr/models/abyss.py
ambr/models/achievement.py
ambr/models/artifact.py
ambr/models/book.py
ambr/models/changelog.py
ambr/models/character.py
ambr/models/character_fetter.py
ambr/models/domain.py
ambr/models/food.py
ambr/models/furniture.py
ambr/models/guides.py
ambr/models/material.py
ambr/models/monster.py
ambr/models/name_card.py
ambr/models/quest.py
ambr/models/tcg.py
ambr/models/upgrade.py
ambr/models/weapon.py
ambr_py-1.8.8.dist-info/METADATA
ambr_py-1.8.8.dist-info/WHEEL
ambr_py-1.8.8.dist-info/licenses/LICENSE
ambr_py-1.8.8.dist-info/RECORD
