Metadata-Version: 2.4
Name: ambr-py
Version: 1.8.8
Summary: Async API wrapper for Project Amber (gi.yatta.moe) written in Python
Project-URL: Homepage, https://github.com/seriaati/ambr
Project-URL: Repository, https://github.com/seriaati/ambr.git
Project-URL: Issues, https://github.com/seriaati/ambr/issues
Project-URL: Documentation, https://gh.seria.moe/ambr
Author-email: seriaati <seria.ati@gmail.com>
License: GNU GENERAL PUBLIC LICENSE
License-File: LICENSE
Requires-Python: >=3.11
Requires-Dist: aiofiles>=24.1.0
Requires-Dist: aiohttp-client-cache[sqlite]>=0.12.3
Requires-Dist: aiohttp>=3.10.9
Requires-Dist: loguru>=0.7.2
Requires-Dist: pydantic>=2.9.2
Provides-Extra: docs
Requires-Dist: mkdocs-material[imaging]>=9.6.11; extra == 'docs'
Requires-Dist: mkdocstrings[python]>=0.29.1; extra == 'docs'
